AUTHORS
LICENSE
MANIFEST.in
README.rst
pytestdoc.py
setup.cfg
setup.py
bin/json2rst
pytest_doc/__init__.py
pytest_doc/plugin.py
pytest_doc.egg-info/PKG-INFO
pytest_doc.egg-info/SOURCES.txt
pytest_doc.egg-info/dependency_links.txt
pytest_doc.egg-info/entry_points.txt
pytest_doc.egg-info/requires.txt
pytest_doc.egg-info/top_level.txt