Metadata-Version: 1.1
Name: pytest-doc
Version: 0.0.1
Summary: A documentation plugin for py.test.
Home-page: http://pytest-doc.readthedocs.org/
Author: Alfred Perlstein
Author-email: alfred@freebsd.org
License: BSD-2-Clause
Platform: UNKNOWN
Classifier: Development Status :: 5 - Production/Stable
Classifier: Intended Audience :: Developers
Classifier: License :: OSI Approved :: BSD License
Classifier: Operating System :: OS Independent
Classifier: Programming Language :: Python
Classifier: Topic :: Software Development :: Testing
Classifier: Programming Language :: Python :: 2.6
Classifier: Programming Language :: Python :: 2.7
Classifier: Programming Language :: Python :: 3.2
Classifier: Programming Language :: Python :: 3.3
Classifier: Programming Language :: Python :: 3.4
